switchlang/__init__.py
switchlang/__switchlang_impl.py
switchlang-0.1.1.dist-info/licenses/LICENSE
switchlang-0.1.1.dist-info/METADATA
switchlang-0.1.1.dist-info/WHEEL
switchlang-0.1.1.dist-info/top_level.txt
switchlang-0.1.1.dist-info/RECORD
